Simulator/__init__.py
Simulator/agent.py
Simulator/flights.py
Simulator/grid.py
Simulator/layout.json
Simulator/simulation.py
airportAI_simulator-0.0.3.data/data/layout/layout.json
airportAI_simulator-0.0.3.dist-info/METADATA
airportAI_simulator-0.0.3.dist-info/WHEEL
airportAI_simulator-0.0.3.dist-info/top_level.txt
airportAI_simulator-0.0.3.dist-info/RECORD
